machine_translation/__init__.py
machine_translation/data.py
machine_translation/model.py
machine_translation/train.py
machine_translation/translate.py
machine_translation/utils.py
machine_translation-0.1.0.dist-info/LICENSE
machine_translation-0.1.0.dist-info/METADATA
machine_translation-0.1.0.dist-info/WHEEL
machine_translation-0.1.0.dist-info/top_level.txt
machine_translation-0.1.0.dist-info/RECORD
