Metadata-Version: 2.1
Name: machine-translation
Version: 0.1.0
Summary: A German-to-English machine translation package using PyTorch
Home-page: https://github.com/yourusername/machine_translation
Author: Sunil Reddy
Author-email: challamalla5sunil@gmail.com
License: UNKNOWN
Platform: UNKNOWN
Classifier: Programming Language :: Python :: 3
Classifier: License :: OSI Approved :: MIT License
Classifier: Operating System :: OS Independent
Requires-Python: >=3.6
License-File: LICENSE
Requires-Dist: torch>=1.9.0
Requires-Dist: datasets>=1.8.0
Requires-Dist: spacy>=3.0.0
Requires-Dist: nltk>=3.5
